django_graflow-0.2.0.dist-info/licenses/LICENCE
graflow/__init__.py
graflow/admin.py
graflow/apps.py
graflow/models.py
graflow/urls.py
graflow/api/README.md
graflow/api/__init__.py
graflow/api/serializers.py
graflow/api/throttling.py
graflow/api/views.py
graflow/graphs/__init__.py
graflow/graphs/base.py
graflow/graphs/flow_state_graph.py
graflow/graphs/registry.py
graflow/management/commands/visualize_graph.py
graflow/migrations/0001_initial.py
graflow/migrations/__init__.py
graflow/storage/README.md
graflow/storage/__init__.py
graflow/storage/base.py
graflow/storage/cache.py
graflow/storage/checkpointer.py
graflow/storage/store.py
django_graflow-0.2.0.dist-info/METADATA
django_graflow-0.2.0.dist-info/WHEEL
django_graflow-0.2.0.dist-info/top_level.txt
django_graflow-0.2.0.dist-info/RECORD
