Metadata-Version: 2.4
Name: django-graflow
Version: 0.2.0
Summary: Django app for building long-running, interactive, and stateful AI workflows using LangGraph
Author: Ali Abbasi
License-Expression: MIT
Project-URL: Homepage, https://github.com/ulern-com/graflow-django
Project-URL: Source, https://github.com/ulern-com/graflow-django
Project-URL: Issues, https://github.com/ulern-com/graflow-django/issues
Keywords: django,langgraph,langchain,rest-api,flows
Requires-Python: >=3.12
License-File: LICENCE
Requires-Dist: Django<7.0,>=5.2
Requires-Dist: djangorestframework<4.0,>=3.15
Requires-Dist: django-extensions<5.0,>=4.1
Requires-Dist: drf-spectacular<1.0,>=0.29.0
Requires-Dist: langgraph<1.0.9,>=1.0.5
Requires-Dist: langgraph-checkpoint-postgres>=3.0.2
Requires-Dist: pydantic>=2.12.5
Requires-Dist: python-dotenv>=1.0
Requires-Dist: orjson>=3.11.5
Provides-Extra: postgres
Requires-Dist: psycopg[binary]>=3.3.0; extra == "postgres"
Provides-Extra: dev
Requires-Dist: coverage[toml]>=7.13.0; extra == "dev"
Requires-Dist: build>=1.3.0; extra == "dev"
Requires-Dist: factory-boy>=3.3.0; extra == "dev"
Requires-Dist: pytest>=9.0.2; extra == "dev"
Requires-Dist: pytest-cov>=5.0; extra == "dev"
Requires-Dist: pytest-django>=4.11.0; extra == "dev"
Requires-Dist: black>=25.12.0; extra == "dev"
Requires-Dist: ruff>=0.14.9; extra == "dev"
Requires-Dist: mypy>=1.19.0; extra == "dev"
Requires-Dist: django-stubs[compatible]>=5.2.8; extra == "dev"
Requires-Dist: types-orjson>=3.6; extra == "dev"
Dynamic: license-file
